prokerala_api/__init__.py
prokerala_api/example.py
prokerala_api-0.1.0.dist-info/LICENSE
prokerala_api-0.1.0.dist-info/METADATA
prokerala_api-0.1.0.dist-info/WHEEL
prokerala_api-0.1.0.dist-info/top_level.txt
prokerala_api-0.1.0.dist-info/RECORD
