Metadata-Version: 2.1
Name: prokerala-api
Version: 0.1.0
Summary: SDK for accessing Prokerala API
Author-email: Joyce Babu <joyce@ennexa.com>
Project-URL: Homepage, https://github.com/prokerala/astrology-api-client-example
Project-URL: Issues, https://github.com/prokerala/astrology-api-client-example/issues
Classifier: Programming Language :: Python :: 3
Classifier: License :: OSI Approved :: MIT License
Classifier: Operating System :: OS Independent
Requires-Python: >=3.0
License-File: LICENSE
